poetry_demo_jerber_new/Models/User.py
poetry_demo_jerber_new/Outer/hello.py
poetry_demo_jerber_new/__init__.py
poetry_demo_jerber_new-0.1.1.dist-info/WHEEL
poetry_demo_jerber_new-0.1.1.dist-info/METADATA
poetry_demo_jerber_new-0.1.1.dist-info/RECORD
