Metadata-Version: 2.1
Name: poetry-demo-jerber-new
Version: 0.1.1
Summary: 
Author: Jeremy Berman
Author-email: jerber@sas.upenn.edu
Requires-Python: >=3.8,<4.0
Classifier: Programming Language :: Python :: 3
Classifier: Programming Language :: Python :: 3.8
Requires-Dist: pydantic (>=1.6.1,<2.0.0)
